scanner_client/__init__.py
scanner_client/detection_rule.py
scanner_client/detection_rule_yaml.py
scanner_client/event_sink.py
scanner_client/example.py
scanner_client/github_sync.py
scanner_client/http_err.py
scanner_client/py.typed
scanner_client/query.py
scanner_client/raw_api/__init__.py
scanner_client/raw_api/api/__init__.py
scanner_client/raw_api/api/detection_rule/__init__.py
scanner_client/raw_api/api/detection_rule/create_detection_rule.py
scanner_client/raw_api/api/detection_rule/delete_detection_rule.py
scanner_client/raw_api/api/detection_rule/get_detection_rule.py
scanner_client/raw_api/api/detection_rule/get_detection_rule_by_sync_key.py
scanner_client/raw_api/api/detection_rule/list_detection_rules.py
scanner_client/raw_api/api/detection_rule/update_detection_rule.py
scanner_client/raw_api/api/detection_rule_yaml/__init__.py
scanner_client/raw_api/api/detection_rule_yaml/run_detection_rule_yaml_tests.py
scanner_client/raw_api/api/detection_rule_yaml/validate_detection_rule_yaml.py
scanner_client/raw_api/api/event_sink/__init__.py
scanner_client/raw_api/api/event_sink/create_event_sink.py
scanner_client/raw_api/api/event_sink/delete_event_sink.py
scanner_client/raw_api/api/event_sink/get_event_sink.py
scanner_client/raw_api/api/event_sink/list_event_sinks.py
scanner_client/raw_api/api/event_sink/update_event_sink.py
scanner_client/raw_api/api/github_repo_sync_source/__init__.py
scanner_client/raw_api/api/github_repo_sync_source/sync_github_repositories.py
scanner_client/raw_api/api/lookup_table_file/__init__.py
scanner_client/raw_api/api/lookup_table_file/create_lookup_table_file.py
scanner_client/raw_api/api/lookup_table_file/delete_lookup_table_file.py
scanner_client/raw_api/api/lookup_table_file/get_lookup_table_file.py
scanner_client/raw_api/api/lookup_table_file/list_lookup_table_files.py
scanner_client/raw_api/api/lookup_table_file/update_lookup_table_file.py
scanner_client/raw_api/api/query/__init__.py
scanner_client-0.1.0rc13.dist-info/LICENSE
scanner_client-0.1.0rc13.dist-info/METADATA
scanner_client-0.1.0rc13.dist-info/WHEEL
scanner_client-0.1.0rc13.dist-info/entry_points.txt
scanner_client-0.1.0rc13.dist-info/RECORD
