Metadata-Version: 2.3
Name: scanner-client
Version: 0.1.0rc13
Summary: Scanner API client for Python
License: Apache-2.0
Author: Scanner, Inc.
Author-email: support@scanner.dev
Requires-Python: >=3.10,<4.0
Classifier: License :: OSI Approved :: Apache Software License
Classifier: Programming Language :: Python :: 3
Classifier: Programming Language :: Python :: 3.10
Classifier: Programming Language :: Python :: 3.11
Classifier: Programming Language :: Python :: 3.12
Classifier: Programming Language :: Python :: 3.13
Requires-Dist: attrs (>=23.2.0,<24.0.0)
Requires-Dist: httpx (>=0.27.0,<0.28.0)
Requires-Dist: python-dateutil (>=2.9.0.post0,<3.0.0)
Project-URL: Documentation, https://docs.scanner.dev
